odoo8_addon_base_delivery_carrier_files-8.0.1.2.5-py3.8-nspkg.pth
odoo_addons/base_delivery_carrier_files/README.rst
odoo_addons/base_delivery_carrier_files/__init__.py
odoo_addons/base_delivery_carrier_files/__openerp__.py
odoo_addons/base_delivery_carrier_files/csv_writer/__init__.py
odoo_addons/base_delivery_carrier_files/csv_writer/unicode_writer.py
odoo_addons/base_delivery_carrier_files/demo/carrier_file_demo.xml
odoo_addons/base_delivery_carrier_files/demo/carrier_file_demo.yml
odoo_addons/base_delivery_carrier_files/generator/__init__.py
odoo_addons/base_delivery_carrier_files/generator/base_line.py
odoo_addons/base_delivery_carrier_files/generator/file_generator.py
odoo_addons/base_delivery_carrier_files/generator/generic_generator.py
odoo_addons/base_delivery_carrier_files/i18n/am.po
odoo_addons/base_delivery_carrier_files/i18n/ar.po
odoo_addons/base_delivery_carrier_files/i18n/base_delivery_carrier_files.pot
odoo_addons/base_delivery_carrier_files/i18n/bg.po
odoo_addons/base_delivery_carrier_files/i18n/bs.po
odoo_addons/base_delivery_carrier_files/i18n/ca.po
odoo_addons/base_delivery_carrier_files/i18n/ca_ES.po
odoo_addons/base_delivery_carrier_files/i18n/cs.po
odoo_addons/base_delivery_carrier_files/i18n/da.po
odoo_addons/base_delivery_carrier_files/i18n/de.po
odoo_addons/base_delivery_carrier_files/i18n/el_GR.po
odoo_addons/base_delivery_carrier_files/i18n/en_GB.po
odoo_addons/base_delivery_carrier_files/i18n/es.po
odoo_addons/base_delivery_carrier_files/i18n/es_AR.po
odoo_addons/base_delivery_carrier_files/i18n/es_CL.po
odoo_addons/base_delivery_carrier_files/i18n/es_CO.po
odoo_addons/base_delivery_carrier_files/i18n/es_CR.po
odoo_addons/base_delivery_carrier_files/i18n/es_DO.po
odoo_addons/base_delivery_carrier_files/i18n/es_EC.po
odoo_addons/base_delivery_carrier_files/i18n/es_MX.po
odoo_addons/base_delivery_carrier_files/i18n/es_PE.po
odoo_addons/base_delivery_carrier_files/i18n/es_PY.po
odoo_addons/base_delivery_carrier_files/i18n/es_VE.po
odoo8_addon_base_delivery_carrier_files-8.0.1.2.5.dist-info/METADATA
odoo8_addon_base_delivery_carrier_files-8.0.1.2.5.dist-info/WHEEL
odoo8_addon_base_delivery_carrier_files-8.0.1.2.5.dist-info/namespace_packages.txt
odoo8_addon_base_delivery_carrier_files-8.0.1.2.5.dist-info/top_level.txt
odoo8_addon_base_delivery_carrier_files-8.0.1.2.5.dist-info/RECORD
